{
    "total":10,
    "subject":[
        {
            "title":"新都桥",
            "url":"https://jiakaihaoren.github.io/mySources/images/background.jpg"
        },
        {
            "title":"新都桥",
            "url":"https://jiakaihaoren.github.io/mySources/images/background.jpg"
        },
        {
            "title":"新都桥",
            "url":"https://jiakaihaoren.github.io/mySources/images/background.jpg"
        },
        {
            "title":"新都桥",
            "url":"https://jiakaihaoren.github.io/mySources/images/background.jpg"
        },
        {
            "title":"新都桥",
            "url":"https://jiakaihaoren.github.io/mySources/images/background.jpg"
        },
        {
            "title":"新都桥",
            "url":"https://jiakaihaoren.github.io/mySources/images/background.jpg"
        },
        {
            "title":"新都桥",
            "url":"https://jiakaihaoren.github.io/mySources/images/background.jpg"
        },
        {
            "title":"新都桥",
            "url":"https://jiakaihaoren.github.io/mySources/images/background.jpg"
        },
        {
            "title":"新都桥",
            "url":"https://jiakaihaoren.github.io/mySources/images/background.jpg"
        },
        {
            "title":"新都桥",
            "url":"https://jiakaihaoren.github.io/mySources/images/background.jpg"
        }
    ]
}